Debug/gmock.lib
Debug/gmock.pdb
Debug/gmock_main.lib
Debug/gmock_main.pdb
Debug/gmock_mainpdb_debug_postfix-NOTFOUND.pdb
Debug/gmockpdb_debug_postfix-NOTFOUND.pdb
Debug/gtest.lib
Debug/gtest.pdb
Debug/gtest_main.lib
Debug/gtest_main.pdb
Debug/gtest_mainpdb_debug_postfix-NOTFOUND.pdb
Debug/gtestpdb_debug_postfix-NOTFOUND.pdb
v_quantum_annealing/__init__.py
v_quantum_annealing/_version.py
v_quantum_annealing/variable_type.py
v_quantum_annealing/__pycache__/__init__.cpython-310.opt-1.pyc
v_quantum_annealing/__pycache__/__init__.cpython-310.pyc
v_quantum_annealing/__pycache__/_version.cpython-310.opt-1.pyc
v_quantum_annealing/__pycache__/_version.cpython-310.pyc
v_quantum_annealing/__pycache__/variable_type.cpython-310.opt-1.pyc
v_quantum_annealing/__pycache__/variable_type.cpython-310.pyc
v_quantum_annealing/model/__init__.py
v_quantum_annealing/model/chimera_model.py
v_quantum_annealing/model/king_graph.py
v_quantum_annealing/model/model.py
v_quantum_annealing/model/__pycache__/__init__.cpython-310.opt-1.pyc
v_quantum_annealing/model/__pycache__/__init__.cpython-310.pyc
v_quantum_annealing/model/__pycache__/chimera_model.cpython-310.opt-1.pyc
v_quantum_annealing/model/__pycache__/chimera_model.cpython-310.pyc
v_quantum_annealing/model/__pycache__/king_graph.cpython-310.opt-1.pyc
v_quantum_annealing/model/__pycache__/king_graph.cpython-310.pyc
v_quantum_annealing/model/__pycache__/model.cpython-310.opt-1.pyc
v_quantum_annealing/model/__pycache__/model.cpython-310.pyc
v_quantum_annealing/sampler/__init__.py
v_quantum_annealing/sampler/base_sa_sample_hubo.py
v_quantum_annealing/sampler/csqa_sampler.py
v_quantum_annealing/sampler/response.py
v_quantum_annealing/sampler/sa_sampler.py
v_quantum_annealing/sampler/sampler.py
v_quantum_annealing/sampler/sqa_sampler.py
v_quantum_annealing/sampler/__pycache__/__init__.cpython-310.opt-1.pyc
v_quantum_annealing/sampler/__pycache__/__init__.cpython-310.pyc
c2isample-0.0.11.dist-info/LICENSE
c2isample-0.0.11.dist-info/METADATA
c2isample-0.0.11.dist-info/WHEEL
c2isample-0.0.11.dist-info/top_level.txt
c2isample-0.0.11.dist-info/RECORD
